{"name":"Player","tabColor":[1,0.800000011920929,0.800000011920929,1],"uiState":{"viewsUIState":[{"scroll":0,"eventSheetView":{"conditionsColumnWidth":150,"conditionNameCellWidth":28,"actionNameCellWidth":28,"fontSizeEm":1}}],"bookmark":false,"eventsUIState":[{"viewsUIState":[{"expanded":true}],"bookmark":false,"children":[{"viewsUIState":[{}],"bookmark":false},{"viewsUIState":[{"expanded":true}],"bookmark":false,"children":[]},{"viewsUIState":[{"expanded":true}],"bookmark":false,"children":[]},{"viewsUIState":[{"expanded":true}],"bookmark":false,"children":[]},{"viewsUIState":[{"expanded":false}],"bookmark":false,"children":[{"viewsUIState":[{"expanded":false}],"bookmark":false,"children":[{"viewsUIState":[{}],"bookmark":false},{"viewsUIState":[{}],"bookmark":false},{"viewsUIState":[{"expanded":true}],"bookmark":false,"children":[]},{"viewsUIState":[{"expanded":true}],"bookmark":false,"children":[]},{"viewsUIState":[{"expanded":true}],"bookmark":false,"children":[]},{"viewsUIState":[{"expanded":true}],"bookmark":false,"children":[]},{"viewsUIState":[{}],"bookmark":false},{"viewsUIState":[{"expanded":true}],"bookmark":false,"children":[]},{"viewsUIState":[{"expanded":true}],"bookmark":false,"children":[{"viewsUIState":[{"expanded":true}],"bookmark":false,"children":[]},{"viewsUIState":[{"expanded":true}],"bookmark":false,"children":[]}]}]},{"viewsUIState":[{"expanded":true}],"bookmark":false,"children":[{"viewsUIState":[{}],"bookmark":false},{"viewsUIState":[{}],"bookmark":false},{"viewsUIState":[{"expanded":true}],"bookmark":false,"children":[{"viewsUIState":[{"expanded":true}],"bookmark":false,"children":[]},{"viewsUIState":[{"expanded":true}],"bookmark":false,"children":[]},{"viewsUIState":[{"expanded":true}],"bookmark":false,"children":[]}]},{"viewsUIState":[{}],"bookmark":false},{"viewsUIState":[{"expanded":true}],"bookmark":false,"children":[]},{"viewsUIState":[{"expanded":true}],"bookmark":false,"children":[]},{"viewsUIState":[{"expanded":true}],"bookmark":false,"children":[]},{"viewsUIState":[{"expanded":true}],"bookmark":false,"children":[]}]}]},{"viewsUIState":[{"expanded":false}],"bookmark":false,"children":[{"viewsUIState":[{"expanded":true}],"bookmark":false,"children":[]}]},{"viewsUIState":[{"expanded":true}],"bookmark":false,"children":[{"viewsUIState":[{"expanded":true}],"bookmark":false,"children":[]}]}]}]}}