{"name":"enemy4","plugin-id":"Sprite","sid":194349561519066,"isGlobal":false,"instanceVariables":[],"behaviorTypes":[],"effectTypes":[],"animations":{"items":[{"frames":[{"width":32,"height":32,"originX":0.5,"originY":0.5,"originalSource":"","exportFormat":"png","exportQuality":0.8,"imageSpriteId":70,"collisionPoly":{"points":[1,1,0,1,0,0,1,0]},"imagePoints":[{"name":"LeftBullet","x":0.8988970588235294,"y":0.4011374080882353},{"name":"RightBullet","x":0.8988970588235294,"y":0.5923138786764706}],"duration":1}],"sid":159197260084899,"name":"Animation 1","isLooping":false,"isPingPong":false,"repeatCount":1,"repeatTo":0,"speed":5}],"subfolders":[]}}